batch_scheduler.py
cli.py
pdfstract-1.0.4.dist-info/licenses/LICENSE
services/__init__.py
services/base.py
services/cli_factory.py
services/db_service.py
services/logger.py
services/ocrfactory.py
services/queue_manager.py
services/results_manager.py
services/converters/__init__.py
services/converters/deepseekocr_transformers_converter.py
services/converters/docling_converter.py
services/converters/marker_converter.py
services/converters/markitdown_converter.py
services/converters/paddleocr_converter.py
services/converters/pymupdf4llm_converter.py
services/converters/pytesseract_converter.py
services/converters/unstructured_converter.py
pdfstract-1.0.4.dist-info/METADATA
pdfstract-1.0.4.dist-info/WHEEL
pdfstract-1.0.4.dist-info/entry_points.txt
pdfstract-1.0.4.dist-info/top_level.txt
pdfstract-1.0.4.dist-info/RECORD
