Metadata-Version: 2.4
Name: pdfstract
Version: 1.0.4
Summary: PDFStract - Unified PDF Extraction & Conversion CLI + Web UI with 10+ extraction libraries
Requires-Python: >=3.11
License-File: LICENSE
Requires-Dist: aiofiles>=24.1.0
Requires-Dist: click>=8.1.0
Requires-Dist: docling>=2.41.0
Requires-Dist: fastapi>=0.116.1
Requires-Dist: jinja2>=3.1.6
Requires-Dist: marker-pdf>=1.8.1
Requires-Dist: markitdown[pdf]>=0.1.2
Requires-Dist: paddleocr[all]>=3.3.2
Requires-Dist: paddlepaddle>=3.2.2; platform_machine != "aarch64"
Requires-Dist: pdf2image>=1.17.0
Requires-Dist: pillow>=10.4.0
Requires-Dist: pymupdf4llm>=0.0.26
Requires-Dist: pypdf2>=3.0.1
Requires-Dist: python-magic>=0.4.27
Requires-Dist: python-multipart>=0.0.20
Requires-Dist: rich>=13.0.0
Requires-Dist: uvicorn[standard]>=0.35.0
Requires-Dist: loguru>=0.7.2
Requires-Dist: transformers>=4.51.1
Requires-Dist: torch>=2.0.0
Requires-Dist: addict>=2.4.0
Requires-Dist: matplotlib>=3.10.7
Requires-Dist: easydict>=1.13
Requires-Dist: pytesseract>=0.3.10
Requires-Dist: unstructured[pdf]>=0.15.0
Dynamic: license-file
